{
  "playersByHall": {
    "hall1": [
      "Иванов Иван Иванович",
      "Петров Петр Петрович",
      "Смирнов Артём Андреевич",      
      "Иванов Иван Иванович",
      "Петров Петр Петрович",
      "Смирнов Артём Андреевич",
      "Иванов Иван Иванович",
      "Петров Петр Петрович",
      "Смирнов Артём Андреевич",      
      "Иванов Иван Иванович",
      "Петров Петр Петрович",
      "Смирнов Артём Андреевич",
      "Кузнецов Илья Владимирович"
    ],
    "hall2": [
      "Сидоров Сидор Сидорович",
      "Фёдоров Дмитрий Валерьевич",
      "Николаев Алексей Петрович"
    ]
  },
  "historyByDate": {
    "2026-04-10": {
      "hall1": [
        "Иванов Иван Иванович",
        "Смирнов Артём Андреевич",
        "Кузнецов Илья Владимирович"
      ],
    "2026-04-11": {
      "hall1": [
        "Иванов Иван Иванович",
        "Смирнов Артём Андреевич",
        "Кузнецов Илья Владимирович"
      ],
    "2026-04-12": {
      "hall1": [
        "Иванов Иван Иванович",
        "Смирнов Артём Андреевич",
        "Кузнецов Илья Владимирович"
      ]
    },
    "2026-04-17": {
      "hall2": [
        "Сидоров Сидор Сидорович",
        "Фёдоров Дмитрий Валерьевич"
      ]
    }
  }
}